buildarr/__init__.py
buildarr/cli/__init__.py
buildarr/cli/compose.py
buildarr/cli/daemon.py
buildarr/cli/exceptions.py
buildarr/cli/main.py
buildarr/cli/run.py
buildarr/cli/test_config.py
buildarr/config/__init__.py
buildarr/config/base.py
buildarr/config/buildarr.py
buildarr/config/exceptions.py
buildarr/config/load.py
buildarr/config/models.py
buildarr/config/post_init_render.py
buildarr/config/render_instance_configs.py
buildarr/config/resolve_instance_dependencies.py
buildarr/config/types.py
buildarr/exceptions.py
buildarr/logging.py
buildarr/manager/__init__.py
buildarr/manager/exceptions.py
buildarr/plugins/__init__.py
buildarr/plugins/dummy/__init__.py
buildarr/plugins/dummy/api.py
buildarr/plugins/dummy/cli.py
buildarr/plugins/dummy/config/__init__.py
buildarr/plugins/dummy/config/settings.py
buildarr/plugins/dummy/config/types.py
buildarr/plugins/dummy/exceptions.py
buildarr/plugins/dummy/manager.py
buildarr/plugins/dummy/plugin.py
buildarr/plugins/dummy/secrets.py
buildarr/plugins/dummy/server.py
buildarr/plugins/dummy/types.py
buildarr/plugins/load.py
buildarr/plugins/models.py
buildarr/plugins/types.py
buildarr/py.typed
buildarr/secrets/__init__.py
buildarr/secrets/base.py
buildarr/secrets/models.py
buildarr/state.py
buildarr/trash.py
buildarr/types.py
buildarr/util.py
buildarr-0.7.1.dist-info/LICENSE
buildarr-0.7.1.dist-info/METADATA
buildarr-0.7.1.dist-info/WHEEL
buildarr-0.7.1.dist-info/entry_points.txt
buildarr-0.7.1.dist-info/RECORD
