Metadata-Version: 2.1
Name: buildarr
Version: 0.7.1
Summary: Constructs and configures Arr PVR stacks
Home-page: https://buildarr.github.io
License: GPL-3.0-or-later
Keywords: buildarr,sonarr,radarr,prowlarr
Author: Callum Dickinson
Author-email: callum.dickinson.nz@gmail.com
Requires-Python: >=3.8,<4.0
Classifier: Development Status :: 4 - Beta
Classifier: Framework :: Pydantic
Classifier: Intended Audience :: End Users/Desktop
Classifier: License :: OSI Approved :: GNU General Public License v3 or later (GPLv3+)
Classifier: Natural Language :: English
Classifier: Operating System :: OS Independent
Classifier: Programming Language :: Python :: 3
Classifier: Programming Language :: Python :: 3.8
Classifier: Programming Language :: Python :: 3.9
Classifier: Programming Language :: Python :: 3.10
Classifier: Programming Language :: Python :: 3.11
Classifier: Programming Language :: Python :: 3.12
Classifier: Topic :: System :: Systems Administration
Classifier: Typing :: Typed
Requires-Dist: aenum
Requires-Dist: click (>=8.0.4)
Requires-Dist: click-params (>=0.4.1)
Requires-Dist: importlib-metadata (>=4.6.0)
Requires-Dist: pydantic[email] (>=1.10.0,<2.0.0)
Requires-Dist: pyyaml (>=6.0)
Requires-Dist: requests (>=2.28.0)
Requires-Dist: schedule (>=1.1.0)
Requires-Dist: stevedore (>=4.0.0)
Requires-Dist: typing-extensions (>=4.0.1)
Requires-Dist: watchdog (>=3.0.0)
Project-URL: Changes, https://buildarr.github.io/release-notes
Project-URL: Documentation, https://buildarr.github.io
Project-URL: Issue Tracker, https://github.com/buildarr/buildarr/issues
Project-URL: Repository, https://github.com/buildarr/buildarr
